<?xml version="1.0" encoding="ISO-8859-1"?>
<xmlObject>
		<speed>5000</speed><!-- Time in milliseconds 3000 = 3 seconds -->
		<width>620</width>
		<height>275</height>
		<displayInfoText>true</displayInfoText>
		<hoverTextBgColor>0xe0e0e0</hoverTextBgColor>
		<hoverTextBgOpacity>1</hoverTextBgOpacity>
		<hoverTextBgHeight>75</hoverTextBgHeight>
		<buttonBgColor>0xe0e0e0</buttonBgColor>
		<buttonTextColor>0xe53039</buttonTextColor>
		<buttonSelBgColor>0xe53039</buttonSelBgColor>
		<buttonSelTextColor>0xe0e0e0</buttonSelTextColor>
		<slide>
			<url>site_images/slideShowFlash/slide1.gif</url>
			<ImageTitle><![CDATA[<h1>Your Slide Title</h1><p class="flash">Your slide second line subtitle goes here on the second line.</p>]]></ImageTitle>
		</slide>
		<slide>
			<url>site_images/slideShowFlash/slide2.gif</url>
			<ImageTitle><![CDATA[<h1>Your Slide Title</h1><p class="flash">Your slide second line subtitle goes here on the second line.</p>]]></ImageTitle>
		</slide>
		<slide>
			<url>site_images/slideShowFlash/slide3.gif</url>
			<ImageTitle><![CDATA[<h1>Your Slide Title</h1><p class="flash">Your slide second line subtitle goes here on the second line.</p>]]></ImageTitle>
		</slide>
		<slide>
			<url>site_images/slideShowFlash/slide4.gif</url>
			<ImageTitle><![CDATA[<h1>Your Slide Title</h1><p class="flash">Your slide second line subtitle goes here on the second line.</p>]]></ImageTitle>
		</slide>
		<slide>
			<url>site_images/slideShowFlash/slide5.gif</url>
			<ImageTitle><![CDATA[<h1>Your Slide Title</h1><p class="flash">Your slide second line subtitle goes here on the second line.</p>]]></ImageTitle>
		</slide>
		<slide>
			<url>site_images/slideShowFlash/slide6.gif</url>
			<ImageTitle><![CDATA[<h1>Your Slide Title</h1><p class="flash">Your slide second line subtitle goes here on the second line.</p>]]></ImageTitle>
		</slide>
		<slide>
			<url>site_images/slideShowFlash/slide7.gif</url>
			<ImageTitle><![CDATA[<h1>Your Slide Title</h1><p class="flash">Your slide second line subtitle goes here on the second line.</p>]]></ImageTitle>
		</slide>
</xmlObject>


			
